krisi/__init__.py
krisi/sharedtypes.py
krisi/analyse/__init__.py
krisi/analyse/correlations.py
krisi/analyse/dataset.py
krisi/analyse/utils.py
krisi/evaluate/__init__.py
krisi/evaluate/assertions.py
krisi/evaluate/benchmark.py
krisi/evaluate/compare.py
krisi/evaluate/group.py
krisi/evaluate/metric.py
krisi/evaluate/score.py
krisi/evaluate/scorecard.py
krisi/evaluate/type.py
krisi/evaluate/utils.py
krisi/evaluate/library_/benchmarking_models.py
krisi/evaluate/library_/default_metrics_classification.py
krisi/evaluate/library_/default_metrics_regression.py
krisi/evaluate/library_/diagrams.py
krisi/evaluate/library_/metric_wrappers.py
krisi/evaluate/library_/registry.py
krisi/report/__init__.py
krisi/report/console.py
krisi/report/graph.py
krisi/report/interactive.py
krisi/report/pdf.py
krisi/report/report.py
krisi/report/type.py
krisi/report/vizualise.py
krisi/report/library/console/diagrams.py
krisi/report/library/pdf_layouts/scorecard/report.css
krisi/report/library/pdf_layouts/scorecard/report.html
krisi/utils/__init__.py
krisi/utils/console_plot.py
krisi/utils/data.py
krisi/utils/enums.py
krisi/utils/environment.py
krisi/utils/io.py
krisi/utils/iterable_helpers.py
krisi/utils/printing.py
krisi/utils/state.py
krisi/utils/devutils/environment_checks.py
krisi/utils/devutils/generate_from_examples.py
krisi/utils/devutils/timing.py
krisi-1.4.4.dist-info/METADATA
krisi-1.4.4.dist-info/WHEEL
krisi-1.4.4.dist-info/licenses/LICENSE
krisi-1.4.4.dist-info/RECORD
