Metadata-Version: 2.1
Name: krisi
Version: 1.4.4
Summary: Testing and Reporting framework for Time Series Analysis
Project-URL: Documentation, https://dream-faster.github.io/krisi
Project-URL: Issues, https://github.com/dream-faster/krisi/issues
Project-URL: Source, https://github.com/dream-faster/krisi
Author-email: Mark Szulyovszky <mark@dreamfaster.ai>, Daniel Szemerey <daniel@dreamfaster.ai>
License: MIT License
License-File: LICENSE
Classifier: Development Status :: 4 - Beta
Classifier: License :: Other/Proprietary License
Classifier: Operating System :: OS Independent
Classifier: Programming Language :: Python
Classifier: Programming Language :: Python :: 3
Classifier: Programming Language :: Python :: 3.8
Classifier: Programming Language :: Python :: 3.9
Classifier: Programming Language :: Python :: 3.10
Requires-Python: >=3.8
Requires-Dist: dill
Requires-Dist: numpy
Requires-Dist: pandas
Requires-Dist: plotext
Requires-Dist: pytest
Requires-Dist: rich
Requires-Dist: scikit-learn
Requires-Dist: tqdm
Requires-Dist: typing-extensions
Provides-Extra: analysis
Requires-Dist: matplotlib; extra == 'analysis'
Requires-Dist: networkx; extra == 'analysis'
Requires-Dist: statsmodels>=0.12.1; extra == 'analysis'
Provides-Extra: docs
Requires-Dist: image; extra == 'docs'
Requires-Dist: mkdocs-autorefs; extra == 'docs'
Requires-Dist: mkdocs-gallery==0.7.6; extra == 'docs'
Requires-Dist: mkdocs-glightbox>=0.3; extra == 'docs'
Requires-Dist: mkdocs-include-markdown-plugin; extra == 'docs'
Requires-Dist: mkdocs-jupyter; extra == 'docs'
Requires-Dist: mkdocs-material; extra == 'docs'
Requires-Dist: mkdocstrings-python; extra == 'docs'
Provides-Extra: plotting
Requires-Dist: dash; extra == 'plotting'
Requires-Dist: jupyter-dash; extra == 'plotting'
Requires-Dist: kaleido; extra == 'plotting'
Requires-Dist: pangocffi; extra == 'plotting'
Requires-Dist: plotly; extra == 'plotting'
Requires-Dist: statsmodels>=0.12.1; extra == 'plotting'
Requires-Dist: weasyprint; extra == 'plotting'
Provides-Extra: quality
Requires-Dist: black~=22.10.0; extra == 'quality'
Requires-Dist: flake8~=4.0.1; extra == 'quality'
Requires-Dist: isort~=5.10.1; extra == 'quality'
Requires-Dist: pre-commit~=2.20.0; extra == 'quality'
Provides-Extra: tests
Requires-Dist: pytest-cov>=4.0; extra == 'tests'
Requires-Dist: pytest~=7.1.2; extra == 'tests'
